Workbook

Sheet Pivot Tables
A3: Row Labels | B3: Sum of Sales Amount
A4: Mar | B4: 6980450
A5: Oct | B5: 6529848
A6: Nov | B6: 6143927
A7: Jun | B7: 5107279
A8: Sep | B8: 5009541
A9: Dec | B9: 4911065
A10: Apr | B10: 4722687
A11: Jul | B11: 4627443
A12: Jan | B12: 4570497
A13: Feb | B13: 4111552
A14: May | B14: 3938444
A15: Aug | B15: 3787358
A16: Grand Total | B16: 60440091
A19: Row Labels | B19: Sum of Sales Amount
A20: West | B20: 16361705
A21: North | B21: 15881091
A22: South | B22: 15835905
A23: East | B23: 12361390
A24: Grand Total | B24: 60440091
A27: Row Labels | B27: Sum of Sales Amount
A28: Mobile | B28: 14430485
A29: Smartwatch | B29: 13301627
A30: Headphones | B30: 13285802
A31: Tablet | B31: 10106750
A32: Laptop | B32: 9315427
A33: Grand Total | B33: 60440091
B36: Values
A37: Row Labels | B37: Sum of Sales Amount | C37: Sum of Profit
A38: Rajiv Kumar | B38: 9156006 | C38: 2506325.7
A39: Aaradhya Singh | B39: 8224411 | C39: 2318112
A40: Raj Nair | B40: 9123966 | C40: 2309723.7
A41: Shiv Dubey | B41: 7330185 | C41: 1864252.9
A42: Neha Sharma | B42: 7099507 | C42: 1702726.2
A43: Aashish Solankhi | B43: 7258004 | C43: 1648137.7
A44: Amit Singh | B44: 6151085 | C44: 1578933.4
A45: Ira Rajdev | B45: 6096927 | C45: 1335275.3
A46: Grand Total | B46: 60440091 | C46: 15263487

Sheet Sales Data Sheet
A1: Order ID | B1: Date | C1: Month | D1: Region | E1: Salesperson | F1: Product | G1: Quantity | H1: Sales Amount | I1: Cost | J1: Profit | K1: Profit Margin
A2: 1001 | B2: 45499 | C2: =TEXT(B2,"mmm") -> Jul | D2: North | E2: Amit Singh | F2: Laptop | G2: 2 | H2: 100000 | I2: 80000 | J2: 20000 | K2: =J2/H2 -> 0.2
A3: 1002 | B3: 45644 | C3: =TEXT(B3,"mmm") -> Dec | D3: South | E3: Neha Sharma | F3: Mobile | G3: 7 | H3: 498660 | I3: 413887.8 | J3: 84772.2 | K3: =J3/H3 -> 0.17
A4: 1003 | B4: 45418 | C4: =TEXT(B4,"mmm") -> May | D4: East | E4: Rajiv Kumar | F4: Tablet | G4: 9 | H4: 155104 | I4: 96164.48 | J4: 58939.52 | K4: =J4/H4 -> 0.38
A5: 1004 | B5: 45593 | C5: =TEXT(B5,"mmm") -> Oct | D5: West | E5: Aaradhya Singh | F5: Smartwatch | G5: 10 | H5: 421293 | I5: 374950.77 | J5: 46342.23 | K5: =J5/H5 -> 0.11
A6: 1005 | B6: 45576 | C6: =TEXT(B6,"mmm") -> Oct | D6: East | E6: Shiv Dubey | F6: Headphones | G6: 2 | H6: 405035 | I6: 344279.75 | J6: 60755.25 | K6: =J6/H6 -> 0.15
A7: 1006 | B7: 45385 | C7: =TEXT(B7,"mmm") -> Apr | D7: East | E7: Aashish Solankhi | F7: Headphones | G7: 10 | H7: 219588 | I7: 184453.92 | J7: 35134.08 | K7: =J7/H7 -> 0.16
A8: 1007 | B8: 45331 | C8: =TEXT(B8,"mmm") -> Feb | D8: West | E8: Raj Nair | F8: Tablet | G8: 1 | H8: 482853 | I8: 391110.93 | J8: 91742.07 | K8: =J8/H8 -> 0.19
A9: 1008 | B9: 45312 | C9: =TEXT(B9,"mmm") -> Jan | D9: South | E9: Ira Rajdev | F9: Laptop | G9: 8 | H9: 165886 | I9: 147638.54 | J9: 18247.46 | K9: =J9/H9 -> 0.11
A10: 1009 | B10: 45415 | C10: =TEXT(B10,"mmm") -> May | D10: East | E10: =INDEX($E$2:$E$9,RANDBETWEEN(1,8)) -> Rajiv Kumar | F10: Laptop | G10: 1 | H10: 297777 | I10: 250132.68 | J10: 47644.32 | K10: =J10/H10 -> 0.16
A11: 1010 | B11: 45355 | C11: =TEXT(B11,"mmm") -> Mar | D11: East | E11: =INDEX($E$2:$E$9,RANDBETWEEN(1,8)) -> Ira Rajdev | F11: Laptop | G11: 5 | H11: 488175 | I11: 351486 | J11: 136689 | K11: =J11/H11 -> 0.28
A12: 1011 | B12: 45543 | C12: =TEXT(B12,"mmm") -> Sep | D12: North | E12: =INDEX($E$2:$E$9,RANDBETWEEN(1,8)) -> Neha Sharma | F12: Headphones | G12: 1 | H12: 242855 | I12: 160284.3 | J12: 82570.7 | K12: =J12/H12 -> 0.34
A13: 1012 | B13: 45435 | C13: =TEXT(B13,"mmm") -> May | D13: West | E13: =INDEX($E$2:$E$9,RANDBETWEEN(1,8)) -> Raj Nair | F13: Headphones | G13: 8 | H13: 193249 | I13: 133341.81 | J13: 59907.19 | K13: =J13/H13 -> 0.31
A14: 1013 | B14: 45482 | C14: =TEXT(B14,"mmm") -> Jul | D14: South | E14: =INDEX($E$2:$E$9,RANDBETWEEN(1,8)) -> Ira Rajdev | F14: Smartwatch | G14: 10 | H14: 458728 | I14: 371569.68 | J14: 87158.32 | K14: =J14/H14 -> 0.19
A15: 1014 | B15: 45348 | C15: =TEXT(B15,"mmm") -> Feb | D15: West | E15: =INDEX($E$2:$E$9,RANDBETWEEN(1,8)) -> Rajiv Kumar | F15: Mobile | G15: 4 | H15: 160726 | I15: 96435.6 | J15: 64290.4 | K15: =J15/H15 -> 0.4
A16: 1015 | B16: 45590 | C16: =TEXT(B16,"mmm") -> Oct | D16: North | E16: =INDEX($E$2:$E$9,RANDBETWEEN(1,8)) -> Neha Sharma | F16: Smartwatch | G16: 8 | H16: 358341 | I16: 304589.85 | J16: 53751.15 | K16: =J16/H16 -> 0.15
A17: 1016 | B17: 45638 | C17: =TEXT(B17,"mmm") -> Dec | D17: East | E17: =INDEX($E$2:$E$9,RANDBETWEEN(1,8)) -> Aaradhya Singh | F17: Mobile | G17: 7 | H17: 289313 | I17: 240129.79 | J17: 49183.21 | K17: =J17/H17 -> 0.17
A18: 1017 | B18: 45618 | C18: =TEXT(B18,"mmm") -> Nov | D18: West | E18: =INDEX($E$2:$E$9,RANDBETWEEN(1,8)) -> Aashish Solankhi | F18: Mobile | G18: 4 | H18: 409069 | I18: 298620.37 | J18: 110448.63 | K18: =J18/H18 -> 0.27
A19: 1018 | B19: 45409 | C19: =TEXT(B19,"mmm") -> Apr | D19: North | E19: =INDEX($E$2:$E$9,RANDBETWEEN(1,8)) -> Aaradhya Singh | F19: Headphones | G19: 6 | H19: 289297 | I19: 243009.48 | J19: 46287.52 | K19: =J19/H19 -> 0.16
A20: 1019 | B20: 45586 | C20: =TEXT(B20,"mmm") -> Oct | D20: North | E20: =INDEX($E$2:$E$9,RANDBETWEEN(1,8)) -> Aashish Solankhi | F20: Tablet | G20: 10 | H20: 189603 | I20: 157370.49 | J20: 32232.51 | K20: =J20/H20 -> 0.17
A21: 1020 | B21: 45521 | C21: =TEXT(B21,"mmm") -> Aug | D21: South | E21: =INDEX($E$2:$E$9,RANDBETWEEN(1,8)) -> Amit Singh | F21: mobile | G21: 3 | H21: 443785 | I21: 368341.55 | J21: 75443.45 | K21: =J21/H21 -> 0.17
... A200: 1199 | B200: 45410 | C200: =TEXT(B200,"mmm") -> Apr | D200: North | E200: =INDEX($E$2:$E$9,RANDBETWEEN(1,8)) -> Ira Rajdev | F200: Laptop | G200: 3 | H200: 415246 | I200: 319739.42 | J200: 95506.58 | K200: =J200/H200 -> 0.23

Sheet Dashboard
A1: Sales Performance Dashboard 2024
A4: Total Sales | D4: Total Profit | G4: Total Orders | J4: Profit Margin
B5: =SUM('Sales Data Sheet'!H2:H200) -> 60440091 | E5: =SUM('Sales Data Sheet'!J2:J200) -> 15263487 | H5: =COUNTA('Sales Data Sheet'!A2:A200) -> 199 | K5: =E5/B5 -> 0.25253911
A36: Dashboard Insight | G36: Dashboard Navigation
A38: ✔ | B38: ="Highest Sales Month: "&'Pivot Tables'!A4 -> Highest Sales Month: Mar
A39: ✔ | B39: ="Best Region: "&'Pivot Tables'!A20 -> Best Region: West
A40: ✔ | B40: ="Best Selling Product: "&'Pivot Tables'!A28 -> Best Selling Product: Mobile
A41: ✔ | B41: ="Top Salesperson: "&'Pivot Tables'!A38 -> Top Salesperson: Rajiv Kumar
